.gitignore
CHANGES.txt
LICENSE.txt
README.md
README.txt
setup.cfg
setup.py
docs/doc.txt
local_scripts/update_version.sh
localcider/.DS_Store
localcider/__init__.py
localcider/plots.py
localcider/sequenceParameters.py
localcider/sequencePermutants.py
localcider.egg-info/PKG-INFO
localcider.egg-info/SOURCES.txt
localcider.egg-info/dependency_links.txt
localcider.egg-info/requires.txt
localcider.egg-info/top_level.txt
localcider/backend/__init__.py
localcider/backend/backendtools.py
localcider/backend/config.py
localcider/backend/keyfile.py
localcider/backend/localciderExceptions.py
localcider/backend/plotting.py
localcider/backend/residue.py
localcider/backend/restable.py
localcider/backend/seqfileparser.py
localcider/backend/sequence.py
localcider/backend/sequenceComplexity.py
localcider/backend/wang_landau.py
localcider/backend/data/__init__.py
localcider/backend/data/aminoacids.py
localcider/backend/data/buildHighComplexitySequences.py
localcider/backend/data/convergenceDist.dat
localcider/backend/data/highComplexitySequences.py
localcider/backend/data/sequence_complexity.dat
localcider/backend/data/sequence_complexity_100iter.dat
localcider/tests/__init__.py
localcider/tests/runtests.py
localcider/tests/testTools.py
localcider/tests/test_complexity.py
localcider/tests/test_plots.py
localcider/tests/test_sequence.py
localcider/tests/test_sequenceParameters.py