Metadata-Version: 1.0
Name: localcider
Version: 0.1.18
Summary: Tools for calculating sequence properties of disordered proteins [from the Pappu Lab at Washington University in St. Louis]
Home-page: http://pappulab.github.io/localCIDER/
Author: Alex Holehouse
Author-email: alex.holehouse@wustl.edu
License: LICENSE.txt
Platform: UNKNOWN
